ewallet/__init__.py
ewallet/asgi.py
ewallet/authentication.py
ewallet/settings.py
ewallet/urls.py
ewallet/wsgi.py
wallet/__init__.py
wallet/admin.py
wallet/apps.py
wallet/models.py
wallet/serializers.py
wallet/signals.py
wallet/urls.py
wallet/views.py
wallet/migrations/0001_initial.py
wallet/migrations/0002_transaction_wallet_tran_wallet__168f5a_idx.py
wallet/migrations/0003_remove_transaction_wallet_tran_wallet__168f5a_idx.py
wallet/migrations/0004_transaction_wallet_tran_wallet__168f5a_idx.py
wallet/migrations/0005_transaction_status.py
wallet/migrations/0006_auditlog.py
wallet/migrations/0007_notification.py
wallet/migrations/0008_transaction_description.py
wallet/migrations/0009_notification_description_alter_auditlog_action.py
wallet/migrations/__init__.py
wallet/migrations/__pycache__/0001_initial.cpython-312.pyc
wallet/migrations/__pycache__/0002_transaction_wallet_tran_wallet__168f5a_idx.cpython-312.pyc
wallet/migrations/__pycache__/0003_remove_transaction_wallet_tran_wallet__168f5a_idx.cpython-312.pyc
wallet/migrations/__pycache__/0004_transaction_wallet_tran_wallet__168f5a_idx.cpython-312.pyc
wallet/migrations/__pycache__/0005_transaction_status.cpython-312.pyc
wallet/migrations/__pycache__/0006_auditlog.cpython-312.pyc
wallet/migrations/__pycache__/0007_notification.cpython-312.pyc
wallet/migrations/__pycache__/0008_transaction_description.cpython-312.pyc
wallet/migrations/__pycache__/0009_notification_description_alter_auditlog_action.cpython-312.pyc
wallet/migrations/__pycache__/__init__.cpython-312.pyc
wallet/tests/__init__.py
wallet/tests/test_auth.py
wallet/tests/test_models.py
wallet/tests/test_transfer.py
wallet/tests/test_views.py
django_wallet_hacrjit-0.1.2.dist-info/METADATA
django_wallet_hacrjit-0.1.2.dist-info/WHEEL
django_wallet_hacrjit-0.1.2.dist-info/top_level.txt
django_wallet_hacrjit-0.1.2.dist-info/RECORD
